saml/__init__.py
saml/_version.py
saml/client.py
saml/signature.py
saml/schema/__init__.py
saml/schema/base.py
saml/schema/meta.py
saml/schema/saml.py
saml/schema/samlp.py
saml/schema/types.py
saml/schema/utils.py
saml_tra-0.9.1.dist-info/LICENSE
saml_tra-0.9.1.dist-info/METADATA
saml_tra-0.9.1.dist-info/WHEEL
saml_tra-0.9.1.dist-info/top_level.txt
saml_tra-0.9.1.dist-info/RECORD
